[
    { "latein": "adulescens", "deutsch": "junger Mann" },
    { "latein": "adducere", "deutsch": "heranführen" },
    { "latein": "adesse", "deutsch": "helfen, da sein" },
    { "latein": "Amphitryon", "deutsch": "Amphitryon (Pflegevater von Herkules)" },
    { "latein": "animadvertere", "deutsch": "bemerken" },
    { "latein": "ante", "deutsch": "vor" },
    { "latein": "apparere", "deutsch": "erscheinen" },
    { "latein": "armatus", "deutsch": "bewaffnet" },
    { "latein": "audacia", "deutsch": "Kühnheit, Wagemut" },
    { "latein": "auxilium", "deutsch": "Hilfe" },
    { "latein": "ave", "deutsch": "sei gegrüßt" },
    { "latein": "augere", "deutsch": "vermehren, steigern" },
    { "latein": "beatus", "deutsch": "glücklich, selig" },
    { "latein": "cogere", "deutsch": "versammeln, zwingen" },
    { "latein": "cogitare", "deutsch": "denken" },
    { "latein": "colere", "deutsch": "verehren, pflegen" },
    { "latein": "commotus", "deutsch": "bewegt, erregt" },
    { "latein": "comparare", "deutsch": "vergleichen" },
    { "latein": "conspicere", "deutsch": "erblicken" },
    { "latein": "confidere", "deutsch": "vertrauen" },
    { "latein": "conficere", "deutsch": "vollenden, erledigen" },
    { "latein": "copiae", "deutsch": "Truppen" },
    { "latein": "corpus", "deutsch": "Körper" },
    { "latein": "custos", "deutsch": "Wächter" },
    { "latein": "cupere", "deutsch": "wünschen, wollen" },
    { "latein": "dea", "deutsch": "Göttin" },
    { "latein": "desiderare", "deutsch": "wünschen, begehren" },
    { "latein": "dicere", "deutsch": "sagen" },
    { "latein": "donum", "deutsch": "Geschenk" },
    { "latein": "dux", "deutsch": "Führer, Anführer" },
    { "latein": "edidit", "deutsch": "veröffentlichte, gab bekannt" },
    { "latein": "equidem", "deutsch": "freilich, allerdings" },
    { "latein": "esse", "deutsch": "sein" },
    { "latein": "Eurystheus", "deutsch": "Eurystheus (König von Mykene)" },
    { "latein": "fallere", "deutsch": "täuschen" },
    { "latein": "femina", "deutsch": "Frau" },
    { "latein": "ferre", "deutsch": "tragen, bringen" },
    { "latein": "flumen", "deutsch": "Fluss" },
    { "latein": "fortiter", "deutsch": "tapfer" },
    { "latein": "fugere", "deutsch": "fliehen" },
    { "latein": "gloria", "deutsch": "Ruhm" },
    { "latein": "homo", "deutsch": "Mensch" },
    { "latein": "honeste", "deutsch": "ehrenhaft" },
    { "latein": "idoneus", "deutsch": "geeignet" },
    { "latein": "immo", "deutsch": "ja sogar, vielmehr" },
    { "latein": "imperium", "deutsch": "Herrschaft, Reich" },
    { "latein": "intellegere", "deutsch": "verstehen, einsehen" },
    { "latein": "interficere", "deutsch": "töten" },
    { "latein": "interim", "deutsch": "inzwischen" },
    { "latein": "ira", "deutsch": "Zorn" },
    { "latein": "iubere", "deutsch": "befehlen" },
    { "latein": "Iuno", "deutsch": "Juno (Gattin Jupiters)" },
    { "latein": "Iuppiter", "deutsch": "Jupiter" },
    { "latein": "iterum", "deutsch": "wieder, erneut" },
    { "latein": "laudare", "deutsch": "loben" },
    { "latein": "labor", "deutsch": "Anstrengung, Mühe" },
    { "latein": "legare", "deutsch": "vererben, vermachen" },
    { "latein": "litterae", "deutsch": "Brief, Schrift" },
    { "latein": "magnus", "deutsch": "groß" },
    { "latein": "manere", "deutsch": "bleiben" },
    { "latein": "mare", "deutsch": "Meer" },
    { "latein": "mens", "deutsch": "Geist, Verstand" },
    { "latein": "minime", "deutsch": "am wenigsten, keineswegs" },
    { "latein": "mirus", "deutsch": "erstaunlich, wunderbar" },
    { "latein": "mittere", "deutsch": "schicken" },
    { "latein": "mortuus", "deutsch": "tot" },
    { "latein": "munus", "deutsch": "Aufgabe, Geschenk" },
    { "latein": "Mycenae", "deutsch": "Mykene (Stadt)" },
    { "latein": "necavit", "deutsch": "tötete" },
    { "latein": "natus", "deutsch": "Sohn" },
    { "latein": "nata", "deutsch": "Tochter" },
    { "latein": "necare", "deutsch": "töten" },
    { "latein": "nobilis", "deutsch": "adlig, edel" },
    { "latein": "non", "deutsch": "nicht" },
    { "latein": "nuper", "deutsch": "neulich" },
    { "latein": "oculus", "deutsch": "Auge" },
    { "latein": "officium", "deutsch": "Pflicht" },
    { "latein": "opes", "deutsch": "Reichtümer" },
    { "latein": "opprimere", "deutsch": "bedrücken, niederdrücken" },
    { "latein": "optare", "deutsch": "wünschen" },
    { "latein": "ornatus", "deutsch": "geschmückt" },
    { "latein": "oraculum", "deutsch": "Orakel" },
    { "latein": "pater", "deutsch": "Vater" },
    { "latein": "pectus", "deutsch": "Brust" },
    { "latein": "per", "deutsch": "durch" },
    { "latein": "petere", "deutsch": "anstreben, angreifen" },
    { "latein": "pessimus", "deutsch": "sehr schlecht, der schlechteste" },
    { "latein": "ponere", "deutsch": "legen, setzen" },
    { "latein": "potens", "deutsch": "mächtig" },
    { "latein": "praesidium", "deutsch": "Schutz, Wachposten" },
    { "latein": "pulcher", "deutsch": "schön" },
    { "latein": "puer", "deutsch": "Junge" },
    { "latein": "purus", "deutsch": "rein" },
    { "latein": "quasi", "deutsch": "gleichsam, gewissermaßen" },
    { "latein": "regere", "deutsch": "lenken, regieren" },
    { "latein": "regina", "deutsch": "Königin" },
    { "latein": "regnum", "deutsch": "Königreich" },
    { "latein": "rex", "deutsch": "König" },
    { "latein": "scribere", "deutsch": "schreiben" },
    { "latein": "se", "deutsch": "sich" },
    { "latein": "servus", "deutsch": "Diener, Sklave" },
    { "latein": "simul", "deutsch": "gleichzeitig" },
    { "latein": "socium", "deutsch": "Gefährten, Verbündeten" },
    { "latein": "spectare", "deutsch": "anschauen" },
    { "latein": "species", "deutsch": "Erscheinung, Aussehen" },
    { "latein": "stabula", "deutsch": "Ställe" },
    { "latein": "statim", "deutsch": "sofort" },
    { "latein": "stercus", "deutsch": "Mist" },
    { "latein": "stragulum", "deutsch": "Teppich" },
    { "latein": "suscipere", "deutsch": "übernehmen, auf sich nehmen" },
    { "latein": "tamen", "deutsch": "dennoch" },
    { "latein": "talis", "deutsch": "solcher" },
    { "latein": "tempus", "deutsch": "Zeit" },
    { "latein": "Thebae", "deutsch": "Theben (Stadt in Griechenland)" },
    { "latein": "tangere", "deutsch": "berühren" },
    { "latein": "tollere", "deutsch": "aufheben, beseitigen" },
    { "latein": "turpis", "deutsch": "hässlich, schändlich" },
    { "latein": "uxor", "deutsch": "Ehefrau" },
    { "latein": "vestis", "deutsch": "Kleidung" },
    { "latein": "vivus", "deutsch": "lebendig" },
    { "latein": "vocare", "deutsch": "rufen" },
    { "latein": "voluntas", "deutsch": "Wille, Absicht" },
    { "latein": "voluptas", "deutsch": "Vergnügen, Lust" },
    { "latein": "volvere", "deutsch": "wälzen, rollen" },
    { "latein": "vox", "deutsch": "Stimme" },
    { "latein": "virtus", "deutsch": "Tugend, Tapferkeit" },
    { "latein": "vulgus", "deutsch": "das (einfache) Volk" }
]
